LICENSE
MANIFEST.in
README.md
multiquery.py
setup.py
multiquery.egg-info/PKG-INFO
multiquery.egg-info/SOURCES.txt
multiquery.egg-info/dependency_links.txt
multiquery.egg-info/entry_points.txt
multiquery.egg-info/requires.txt
multiquery.egg-info/top_level.txt