Metadata-Version: 1.1
Name: multiquery
Version: 0.0.2
Summary: Runs a single SQL query against a set of databases concatenates the results together.
Home-page: https://github.org/halfak/multiquery
Author: Aaron Halfaker
Author-email: aaron.halfaker@gmail.com
License: The MIT License (MIT)
